AUTHORS
ChangeLog
LICENSE
README.md
requirements.txt
setup.cfg
setup.py
test-requirements.txt
sandbox/fractions/run_al_fractions.py
sandbox/fractions/run_dual_decision_tree.py
sandbox/fractions/run_ppo_fractions.py
sandbox/fractions/train_ppo_number.py
sandbox/fractions/train_ppo_operator.py
sandbox/fractions/tune_ppo_number.py
sandbox/fractions/tune_ppo_operator.py
sandbox/multicolumn/run_al.py
sandbox/multicolumn/run_cobweb_multi.py
sandbox/multicolumn/run_decision_tree_multi-v1.py
sandbox/multicolumn/run_dual_decision_tree_multi.py
sandbox/multicolumn/run_ppo_multi-v0.py
sandbox/multicolumn/run_ppo_multi-v1.py
sandbox/multicolumn/run_ppo_multi-v2.py
sandbox/multicolumn/run_ppo_multi-v3.py
sandbox/multicolumn/run_single_decision_tree_multi.py
sandbox/multicolumn/run_single_dqn.py
sandbox/multicolumn/train_ppo_number.py
sandbox/multicolumn/train_ppo_operator.py
sandbox/multicolumn/tune_ppo_number.py
sandbox/multicolumn/tune_ppo_operator.py
tutorenvs/__init__.py
tutorenvs/fractions.py
tutorenvs/fractions_example.txt
tutorenvs/multicolumn.py
tutorenvs/utils.py
tutorgym.egg-info/PKG-INFO
tutorgym.egg-info/SOURCES.txt
tutorgym.egg-info/dependency_links.txt
tutorgym.egg-info/pbr.json
tutorgym.egg-info/requires.txt
tutorgym.egg-info/top_level.txt